wagtailstreamforms/__init__.py
wagtailstreamforms/blocks.py
wagtailstreamforms/conf.py
wagtailstreamforms/fields.py
wagtailstreamforms/forms.py
wagtailstreamforms/hooks.py
wagtailstreamforms/serializers.py
wagtailstreamforms/streamfield.py
wagtailstreamforms/urls.py
wagtailstreamforms/wagtail_hooks.py
wagtailstreamforms/wagtailstreamforms_fields.py
wagtailstreamforms/wagtailstreamforms_hooks.py
wagtailstreamforms/locale/es/LC_MESSAGES/django.mo
wagtailstreamforms/locale/es/LC_MESSAGES/django.po
wagtailstreamforms/locale/nl/LC_MESSAGES/django.mo
wagtailstreamforms/locale/nl/LC_MESSAGES/django.po
wagtailstreamforms/locale/tr/LC_MESSAGES/django.mo
wagtailstreamforms/locale/tr/LC_MESSAGES/django.po
wagtailstreamforms/management/__init__.py
wagtailstreamforms/management/commands/__init__.py
wagtailstreamforms/management/commands/prunesubmissions.py
wagtailstreamforms/migrations/0001_initial.py
wagtailstreamforms/migrations/0002_form_site.py
wagtailstreamforms/migrations/0003_alter_form_fields.py
wagtailstreamforms/migrations/__init__.py
wagtailstreamforms/models/__init__.py
wagtailstreamforms/models/abstract.py
wagtailstreamforms/models/file.py
wagtailstreamforms/models/form.py
wagtailstreamforms/models/submission.py
wagtailstreamforms/templates/streamforms/advanced_settings.html
wagtailstreamforms/templates/streamforms/confirm_copy.html
wagtailstreamforms/templates/streamforms/confirm_delete.html
wagtailstreamforms/templates/streamforms/form_block.html
wagtailstreamforms/templates/streamforms/index_submissions.html
wagtailstreamforms/templates/streamforms/list_submissions.html
wagtailstreamforms/templates/streamforms/non_existent_form.html
wagtailstreamforms/templates/streamforms/partials/form_field.html
wagtailstreamforms/templates/streamforms/partials/pagination_nav.html
wagtailstreamforms/templates/streamforms/wagtailadmin/shared/datetimepicker_translations.html
wagtailstreamforms/templatetags/__init__.py
wagtailstreamforms/templatetags/streamforms_tags.py
wagtailstreamforms-5.2.6.dist-info/licenses/LICENSE
wagtailstreamforms-5.2.6.dist-info/METADATA
wagtailstreamforms-5.2.6.dist-info/WHEEL
wagtailstreamforms-5.2.6.dist-info/top_level.txt
wagtailstreamforms-5.2.6.dist-info/RECORD
