Metadata-Version: 2.4
Name: wagtailstreamforms
Version: 5.2.6
Author-email: Lab Digital BV <info@labdigital.nl>
License: Proprietary
Classifier: License :: Other/Proprietary License
Classifier: Programming Language :: Python
Classifier: Programming Language :: Python :: 3
Classifier: Programming Language :: Python :: 3.9
Classifier: Programming Language :: Python :: 3.10
Classifier: Programming Language :: Python :: 3.11
Classifier: Programming Language :: Python :: 3.12
Classifier: Programming Language :: Python :: 3.13
Requires-Python: >=3.9
License-File: LICENSE
Requires-Dist: wagtail<8.0,>=6.0
Requires-Dist: Unidecode<2.0,>=0.04.14
Requires-Dist: wagtail-generic-chooser>=0.7.0
Requires-Dist: wagtail-modeladmin>=2.2.0
Requires-Dist: django-recaptcha>=4.0.0
Requires-Dist: psycopg>=3.2.9
Requires-Dist: tox>=4.26.0
Dynamic: license-file
